[
  {
    "id": "43764692283",
    "name": "SSB Sport",
    "url": "https://www.eventbrite.fr/o/ssb-sport-43764692283"
  },
  {
    "id": "120695636480",
    "name": "Meetic",
    "url": "https://www.eventbrite.com/o/meetic-120695636480"
  },
  {
    "id": "86571929973",
    "name": "Élise Sénéchal - Atelier Pigmenterre",
    "url": "https://www.eventbrite.fr/o/elise-senechal-atelier-pigmenterre-86571929973"
  },
  {
    "id": "69138574783",
    "name": "Zesoiree",
    "url": "https://www.eventbrite.fr/o/zesoiree-69138574783"
  },
  {
    "id": "8128770855",
    "name": "France Digitale",
    "url": "https://www.eventbrite.fr/o/france-digitale-8128770855"
  },
  {
    "id": "77328113053",
    "name": "NostalJam",
    "url": "https://www.eventbrite.fr/o/nostaljam-77328113053"
  },
  {
    "id": "75434802003",
    "name": "Holiclay Céramique",
    "url": "https://www.eventbrite.com/o/holiclay-ceramique-75434802003"
  },
  {
    "id": "120623894779",
    "name": "Les foulées vertes",
    "url": "https://www.eventbrite.com/o/les-foulees-vertes-120623894779"
  },
  {
    "id": "13448477951",
    "name": "Melting Art Gallery",
    "url": "https://www.eventbrite.fr/o/melting-art-gallery-13448477951"
  },
  {
    "id": "113705720191",
    "name": "City Whispers",
    "url": "https://www.eventbrite.fr/o/city-whispers-113705720191"
  },
  {
    "id": "14794357619",
    "name": "Iberica",
    "url": "https://www.eventbrite.fr/o/iberica-14794357619"
  },
  {
    "id": "7346138511",
    "name": "La Fresque des Réseaux Sociaux",
    "url": "https://www.eventbrite.fr/o/la-fresque-des-reseaux-sociaux-7346138511"
  },
  {
    "id": "69041862503",
    "name": "Mademoiselle Cocotte",
    "url": "https://www.eventbrite.com/o/mademoiselle-cocotte-69041862503"
  },
  {
    "id": "121441707675",
    "name": "Spaice",
    "url": "https://www.eventbrite.fr/o/spaice-121441707675"
  }
]